bootstrap_submenu/__init__.py
bootstrap_submenu/static/submenu/bootstrap-submenu.js
bootstrap_submenu/static/submenu/bootstrap-submenu.min.css
bootstrap_submenu/templatetags/__init__.py
bootstrap_submenu/templatetags/bootstrap_submenu.py
django_bootstrap_submenu-0.1.7.dist-info/DESCRIPTION.rst
django_bootstrap_submenu-0.1.7.dist-info/METADATA
django_bootstrap_submenu-0.1.7.dist-info/RECORD
django_bootstrap_submenu-0.1.7.dist-info/WHEEL
django_bootstrap_submenu-0.1.7.dist-info/metadata.json
django_bootstrap_submenu-0.1.7.dist-info/top_level.txt
