Metadata-Version: 2.0
Name: django-bootstrap-submenu
Version: 0.1.7
Summary: bootstrap-submenu
Home-page: http://sdcto.cn
Author: depth.net(深度网络)
Author-email: yuerthe9@aliyun.com
License: MIT License
Keywords: bootstrap,submenu
Platform: UNKNOWN
Classifier: Development Status :: 3 - Alpha
Classifier: Environment :: Web Environment
Classifier: Intended Audience :: End Users/Desktop
Classifier: Natural Language :: English
Classifier: Operating System :: OS Independent
Classifier: Framework :: Django
Classifier: Programming Language :: Python
Classifier: Topic :: Software Development :: Libraries
Classifier: License :: OSI Approved :: MIT License
Requires-Dist: django (>=1.8.7)
